CHANGES.txt
MANIFEST.in
README.txt
requirements.txt
setup.py
docs/HISTORY.txt
wheelcms_categories/__init__.py
wheelcms_categories/models.py
wheelcms_categories.egg-info/PKG-INFO
wheelcms_categories.egg-info/SOURCES.txt
wheelcms_categories.egg-info/dependency_links.txt
wheelcms_categories.egg-info/namespace_packages.txt
wheelcms_categories.egg-info/not-zip-safe
wheelcms_categories.egg-info/requires.txt
wheelcms_categories.egg-info/top_level.txt
wheelcms_categories/static/img/icons/categories.png
wheelcms_categories/static/img/icons/category.png
wheelcms_categories/templates/wheelcms_categories/category_view.html
wheelcms_categories/tests/conftest.py
wheelcms_categories/tests/test_categories.py