Metadata-Version: 1.1
Name: wheelcms-categories
Version: 0.8
Summary: WheelCMS category implementation
Home-page: http://github.com/wheelcms/wheelcms_categories
Author: Ivo van der Wijk
Author-email: wheelcms@in.m3r.nl
License: BSD
Platform: UNKNOWN
Classifier: Programming Language :: Python
